data_memory.v
module data_memory(

    input clk,

    input mem_read,
    input mem_write,

    input [31:0] address,

    input [31:0] write_data,

    output reg [31:0] read_data

);

    reg [31:0] memory [0:255];

    always @(*) begin

        if(mem_read)
            read_data = memory[address[31:2]];
        else
            read_data = 32'b0;

    end

    always @(posedge clk) begin

        if(mem_write)
            memory[address[31:2]] <= write_data;

    end

endmodule

alu.v
module alu(

    input [31:0] A,
    input [31:0] B,

    input [2:0] sel,

    output reg [31:0] Y,

    output reg carry,
    output reg zero

);

    reg [32:0] temp;

    always @(*) begin

        Y = 32'b0;
        carry = 1'b0;
        temp = 33'b0;

        case(sel)

            3'b000: begin
                temp = A + B;
                Y = temp[31:0];
                carry = temp[32];
            end

            3'b001: begin
                temp = A - B;
                Y = temp[31:0];
                carry = temp[32];
            end

            3'b010: begin
                Y = A & B;
            end

            3'b011: begin
                Y = A | B;
            end

            3'b100: begin
                Y = A ^ B;
            end

            3'b101: begin
                Y = ~A;
            end

            3'b110: begin
                Y = A << 1;
            end

            3'b111: begin
                Y = A >> 1;
            end

        endcase

        zero = (Y == 32'b0);

    end

endmodule

alu_control.v
module alu_control(

    input [2:0] alu_op,
    input [2:0] funct3,
    input [6:0] funct7,

    output reg [2:0] alu_sel

);

always @(*) begin

    case(alu_op)

        // ADD
        3'b000:
            alu_sel = 3'b000;

        // SUB
        3'b001:
            alu_sel = 3'b001;

        // Decode R-Type
        3'b010:
        begin

            case({funct7,funct3})

                {7'b0000000,3'b000}:
                    alu_sel = 3'b000; // ADD

                {7'b0100000,3'b000}:
                    alu_sel = 3'b001; // SUB

                {7'b0000000,3'b111}:
                    alu_sel = 3'b010; // AND

                {7'b0000000,3'b110}:
                    alu_sel = 3'b011; // OR

                {7'b0000000,3'b100}:
                    alu_sel = 3'b100; // XOR

                default:
                    alu_sel = 3'b000;

            endcase

        end

        default:
            alu_sel = 3'b000;

    endcase

end

endmodule

sign_extend.v
module sign_extend(

    input [31:0] instruction,

    output [31:0] immediate

);

assign immediate =
    {{20{instruction[31]}}, instruction[31:20]};

endmodule

register_file.v
module register_file(

    input clk,
    input reg_write,

    input [4:0] rs1,
    input [4:0] rs2,

    input [4:0] rd,

    input [31:0] write_data,

    output [31:0] read_data1,
    output [31:0] read_data2

);

    // 32 registers of 32 bits each
    reg [31:0] registers [0:31];

    // Read ports (Combinational)
    assign read_data1 = registers[rs1];
    assign read_data2 = registers[rs2];

    // Write port (Sequential)
    always @(posedge clk)
    begin

        if(reg_write && (rd != 5'd0))
            registers[rd] <= write_data;

        // Keep x0 permanently zero
        registers[0] <= 32'b0;

    end
integer i;

initial begin
    for(i = 0; i < 32; i = i + 1)
        registers[i] = 32'b0;
end
endmodule

control_unit.v
module control_unit(

    input [6:0] opcode,

    output reg reg_write,
    output reg mem_read,
    output reg mem_write,
    output reg alu_src,
    output reg branch,
    output reg mem_to_reg,

    output reg [2:0] alu_op

);

always @(*) begin

    reg_write = 0;
    mem_read = 0;
    mem_write = 0;
    alu_src = 0;
    branch = 0;
    mem_to_reg = 0;
    alu_op = 3'b000;

    case(opcode)

        // R-Type
        7'b0110011: begin
            reg_write = 1;
            alu_op = 3'b010;
        end

        // ADDI
        7'b0010011: begin
            reg_write = 1;
            alu_src = 1;
            alu_op = 3'b000;
        end

        // LW
        7'b0000011: begin
            reg_write = 1;
            mem_read = 1;
            alu_src = 1;
            mem_to_reg = 1;
            alu_op = 3'b000;
        end

        // SW
        7'b0100011: begin
            mem_write = 1;
            alu_src = 1;
            alu_op = 3'b000;
        end

        // BEQ
        7'b1100011: begin
            branch = 1;
            alu_op = 3'b001;
        end

    endcase

end

endmodule

instruction_decoder.v
module instruction_decoder(

    input [31:0] instruction,

    output [6:0] opcode,
    output [4:0] rd,
    output [2:0] funct3,
    output [4:0] rs1,
    output [4:0] rs2,
    output [6:0] funct7

);

assign opcode = instruction[6:0];

assign rd     = instruction[11:7];

assign funct3 = instruction[14:12];

assign rs1    = instruction[19:15];

assign rs2    = instruction[24:20];

assign funct7 = instruction[31:25];

endmodule

instruction_memory.v
module instruction_memory(

    input  [31:0] address,
    output reg [31:0] instruction

);

    reg [31:0] memory [0:255];

   initial begin

    // x1 = 10
    memory[0] = 32'h00A00093;

    // x2 = 20
    memory[1] = 32'h01400113;

    // x3 = x1 + x2
    memory[2] = 32'h002081B3;

    end
    always @(*) begin
        instruction = memory[address[31:2]];
    end

endmodule

pc.v
module pc(
    input clk,
    input reset,
    input [31:0]next_pc,
    output reg [31:0]pc_out
);

always @(posedge clk)
begin
    if(reset)
    pc_out <= 32'b0;
    else
    pc_out <= next_pc;
end

endmodule

cpu_top.v
module cpu_top(
    input clk,
    input reset
);

wire [31:0] pc_out;
wire [31:0] next_pc;

wire [31:0] instruction;

wire [6:0] opcode;
wire [4:0] rd;
wire [2:0] funct3;
wire [4:0] rs1;
wire [4:0] rs2;
wire [6:0] funct7;

wire reg_write;
wire mem_read;
wire mem_write;
wire alu_src;
wire branch;
wire mem_to_reg;

wire [2:0] alu_op;
wire [2:0] alu_sel;

wire [31:0] read_data1;
wire [31:0] read_data2;

wire [31:0] immediate;

wire [31:0] alu_input_b;
wire [31:0] alu_result;

wire carry;
wire zero;

wire [31:0] memory_data;
wire [31:0] write_back_data;

// normal execution : PC = PC + 4
assign next_pc = pc_out + 32'd4;

// select second ALU operand
assign alu_input_b =
    (alu_src) ? immediate : read_data2;

// select data to write back
assign write_back_data =
    (mem_to_reg) ? memory_data : alu_result;


// Program Counter
pc pc_inst(
    .clk(clk),
    .reset(reset),
    .next_pc(next_pc),
    .pc_out(pc_out)
);

// Instruction Memory
instruction_memory imem(
    .address(pc_out),
    .instruction(instruction)
);

// Decode instruction fields
instruction_decoder decoder(
    .instruction(instruction),
    .opcode(opcode),
    .rd(rd),
    .funct3(funct3),
    .rs1(rs1),
    .rs2(rs2),
    .funct7(funct7)
);

// Generate control signals
control_unit ctrl(
    .opcode(opcode),
    .reg_write(reg_write),
    .mem_read(mem_read),
    .mem_write(mem_write),
    .alu_src(alu_src),
    .branch(branch),
    .mem_to_reg(mem_to_reg),
    .alu_op(alu_op)
);

// Register file
register_file rf(
    .clk(clk),
    .reg_write(reg_write),
    .rs1(rs1),
    .rs2(rs2),
    .rd(rd),
    .write_data(write_back_data),
    .read_data1(read_data1),
    .read_data2(read_data2)
);

// Immediate generator
sign_extend se(
    .instruction(instruction),
    .immediate(immediate)
);

// ALU control
alu_control alu_ctrl(
    .alu_op(alu_op),
    .funct3(funct3),
    .funct7(funct7),
    .alu_sel(alu_sel)
);

// Execute stage
alu alu_inst(
    .A(read_data1),
    .B(alu_input_b),
    .sel(alu_sel),
    .Y(alu_result),
    .carry(carry),
    .zero(zero)
);

// Data memory
data_memory dmem(
    .clk(clk),
    .mem_read(mem_read),
    .mem_write(mem_write),
    .address(alu_result),
    .write_data(read_data2),
    .read_data(memory_data)
);

endmodule

testbench.v
`timescale 1ns/1ps

module tb_cpu;

reg clk;
reg reset;

cpu_top dut(
    .clk(clk),
    .reset(reset)
);

// generate clock
always #5 clk = ~clk;

initial begin

    clk = 0;
    reset = 1;

    #10;
    reset = 0;

    #200;

    $finish;

end

// waveform dump
initial begin
    $dumpfile("cpu.vcd");
    $dumpvars(0, tb_cpu);
end

initial begin

    $monitor(
        "Time=%0t PC=%h Instr=%h x1=%d x2=%d x3=%d",
        $time,
        dut.pc_out,
        dut.instruction,
        dut.rf.registers[1],
        dut.rf.registers[2],
        dut.rf.registers[3]
    );

end
endmodule

cpu.vcd
$date
	Tue Jun 16 22:03:03 2026
$end
$version
	Icarus Verilog
$end
$timescale
	1ps
$end
$scope module tb_cpu $end
$var reg 1 ! clk $end
$var reg 1 " reset $end
$scope module dut $end
$var wire 1 ! clk $end
$var wire 1 " reset $end
$var wire 1 # zero $end
$var wire 32 $ write_back_data [31:0] $end
$var wire 5 % rs2 [4:0] $end
$var wire 5 & rs1 [4:0] $end
$var wire 1 ' reg_write $end
$var wire 32 ( read_data2 [31:0] $end
$var wire 32 ) read_data1 [31:0] $end
$var wire 5 * rd [4:0] $end
$var wire 32 + pc_out [31:0] $end
$var wire 7 , opcode [6:0] $end
$var wire 32 - next_pc [31:0] $end
$var wire 32 . memory_data [31:0] $end
$var wire 1 / mem_write $end
$var wire 1 0 mem_to_reg $end
$var wire 1 1 mem_read $end
$var wire 32 2 instruction [31:0] $end
$var wire 32 3 immediate [31:0] $end
$var wire 7 4 funct7 [6:0] $end
$var wire 3 5 funct3 [2:0] $end
$var wire 1 6 carry $end
$var wire 1 7 branch $end
$var wire 1 8 alu_src $end
$var wire 3 9 alu_sel [2:0] $end
$var wire 32 : alu_result [31:0] $end
$var wire 3 ; alu_op [2:0] $end
$var wire 32 < alu_input_b [31:0] $end
$scope module alu_ctrl $end
$var wire 7 = funct7 [6:0] $end
$var wire 3 > funct3 [2:0] $end
$var wire 3 ? alu_op [2:0] $end
$var reg 3 @ alu_sel [2:0] $end
$upscope $end
$scope module alu_inst $end
$var wire 32 A B [31:0] $end
$var wire 3 B sel [2:0] $end
$var wire 32 C A [31:0] $end
$var reg 32 D Y [31:0] $end
$var reg 1 6 carry $end
$var reg 33 E temp [32:0] $end
$var reg 1 # zero $end
$upscope $end
$scope module ctrl $end
$var wire 7 F opcode [6:0] $end
$var reg 3 G alu_op [2:0] $end
$var reg 1 8 alu_src $end
$var reg 1 7 branch $end
$var reg 1 1 mem_read $end
$var reg 1 0 mem_to_reg $end
$var reg 1 / mem_write $end
$var reg 1 ' reg_write $end
$upscope $end
$scope module decoder $end
$var wire 5 H rs2 [4:0] $end
$var wire 5 I rs1 [4:0] $end
$var wire 5 J rd [4:0] $end
$var wire 7 K opcode [6:0] $end
$var wire 32 L instruction [31:0] $end
$var wire 7 M funct7 [6:0] $end
$var wire 3 N funct3 [2:0] $end
$upscope $end
$scope module dmem $end
$var wire 32 O address [31:0] $end
$var wire 1 ! clk $end
$var wire 1 1 mem_read $end
$var wire 1 / mem_write $end
$var wire 32 P write_data [31:0] $end
$var reg 32 Q read_data [31:0] $end
$upscope $end
$scope module imem $end
$var wire 32 R address [31:0] $end
$var reg 32 S instruction [31:0] $end
$upscope $end
$scope module pc_inst $end
$var wire 1 ! clk $end
$var wire 32 T next_pc [31:0] $end
$var wire 1 " reset $end
$var reg 32 U pc_out [31:0] $end
$upscope $end
$scope module rf $end
$var wire 1 ! clk $end
$var wire 5 V rd [4:0] $end
$var wire 32 W read_data1 [31:0] $end
$var wire 32 X read_data2 [31:0] $end
$var wire 1 ' reg_write $end
$var wire 5 Y rs1 [4:0] $end
$var wire 5 Z rs2 [4:0] $end
$var wire 32 [ write_data [31:0] $end
$var integer 32 \ i [31:0] $end
$upscope $end
$scope module se $end
$var wire 32 ] instruction [31:0] $end
$var wire 32 ^ immediate [31:0] $end
$upscope $end
$upscope $end
$upscope $end
$enddefinitions $end
#0
$dumpvars
bx ^
bx ]
b100000 \
bx [
bx Z
bx Y
bx X
bx W
bx V
bx U
bx T
bx S
bx R
bx Q
bx P
bx O
bx N
bx M
bx L
bx K
bx J
bx I
bx H
bx G
bx F
bx E
bx D
bx C
bx B
bx A
bx @
bx ?
bx >
bx =
bx <
bx ;
bx :
bx 9
x8
x7
x6
bx 5
bx 4
bx 3
bx 2
x1
x0
x/
bx .
bx -
bx ,
bx +
bx *
bx )
bx (
x'
bx &
bx %
bx $
x#
1"
0!
$end
#5000
b1010 $
b1010 [
0#
b0 .
b0 Q
b1010 <
b1010 A
b1010 E
06
b1010 :
b1010 D
b1010 O
b0 9
b0 @
b0 B
b0 ;
b0 ?
b0 G
00
07
18
0/
01
1'
b1010 3
b1010 ^
b0 4
b0 =
b0 M
b0 (
b0 P
b0 X
b1010 %
b1010 H
b1010 Z
b0 )
b0 C
b0 W
b0 &
b0 I
b0 Y
b0 5
b0 >
b0 N
b1 *
b1 J
b1 V
b10011 ,
b10011 F
b10011 K
b101000000000000010010011 2
b101000000000000010010011 L
b101000000000000010010011 S
b101000000000000010010011 ]
b100 -
b100 T
b0 +
b0 R
b0 U
1!
#10000
0!
0"
#15000
b10100 $
b10100 [
b10100 E
b10100 :
b10100 D
b10100 O
b10100 <
b10100 A
b10100 3
b10100 ^
b10100 %
b10100 H
b10100 Z
b10 *
b10 J
b10 V
b1010000000000000100010011 2
b1010000000000000100010011 L
b1010000000000000100010011 S
b1010000000000000100010011 ]
b1000 -
b1000 T
b100 +
b100 R
b100 U
1!
#20000
0!
#25000
b11110 $
b11110 [
b11110 E
b11110 :
b11110 D
b11110 O
b10 ;
b10 ?
b10 G
08
1'
b10 3
b10 ^
b10100 (
b10100 P
b10100 X
b10 %
b10 H
b10 Z
b1010 )
b1010 C
b1010 W
b1 &
b1 I
b1 Y
b11 *
b11 J
b11 V
b110011 ,
b110011 F
b110011 K
b1000001000000110110011 2
b1000001000000110110011 L
b1000001000000110110011 S
b1000001000000110110011 ]
b1100 -
b1100 T
b1000 +
b1000 R
b1000 U
1!
#30000
0!
#35000
bx $
bx [
bx <
bx A
x#
x6
bx E
bx :
bx D
bx O
b0 ;
b0 ?
b0 G
0'
bx 3
bx ^
bx 4
bx =
bx M
bx (
bx P
bx X
bx %
bx H
bx Z
bx )
bx C
bx W
bx &
bx I
bx Y
bx 5
bx >
bx N
bx *
bx J
bx V
bx ,
bx F
bx K
bx 2
bx L
bx S
bx ]
b10000 -
b10000 T
b1100 +
b1100 R
b1100 U
1!
#40000
0!
#45000
b10100 -
b10100 T
b10000 +
b10000 R
b10000 U
1!
#50000
0!
#55000
b11000 -
b11000 T
b10100 +
b10100 R
b10100 U
1!
#60000
0!
#65000
b11100 -
b11100 T
b11000 +
b11000 R
b11000 U
1!
#70000
0!
#75000
b100000 -
b100000 T
b11100 +
b11100 R
b11100 U
1!
#80000
0!
#85000
b100100 -
b100100 T
b100000 +
b100000 R
b100000 U
1!
#90000
0!
#95000
b101000 -
b101000 T
b100100 +
b100100 R
b100100 U
1!
#100000
0!
#105000
b101100 -
b101100 T
b101000 +
b101000 R
b101000 U
1!
#110000
0!
#115000
b110000 -
b110000 T
b101100 +
b101100 R
b101100 U
1!
#120000
0!
#125000
b110100 -
b110100 T
b110000 +
b110000 R
b110000 U
1!
#130000
0!
#135000
b111000 -
b111000 T
b110100 +
b110100 R
b110100 U
1!
#140000
0!
#145000
b111100 -
b111100 T
b111000 +
b111000 R
b111000 U
1!
#150000
0!
#155000
b1000000 -
b1000000 T
b111100 +
b111100 R
b111100 U
1!
#160000
0!
#165000
b1000100 -
b1000100 T
b1000000 +
b1000000 R
b1000000 U
1!
#170000
0!
#175000
b1001000 -
b1001000 T
b1000100 +
b1000100 R
b1000100 U
1!
#180000
0!
#185000
b1001100 -
b1001100 T
b1001000 +
b1001000 R
b1001000 U
1!
#190000
0!
#195000
b1010000 -
b1010000 T
b1001100 +
b1001100 R
b1001100 U
1!
#200000
0!
#205000
b1010100 -
b1010100 T
b1010000 +
b1010000 R
b1010000 U
1!
